dns_archiver/__main__.py
dns_archiver/__version__.py
dns_archiver-0.3.0.dist-info/METADATA
dns_archiver-0.3.0.dist-info/WHEEL
dns_archiver-0.3.0.dist-info/entry_points.txt
dns_archiver-0.3.0.dist-info/RECORD
