Metadata-Version: 2.4
Name: dns-archiver
Version: 0.3.0
Summary: A CLI tool to dump DNS records into an archive
Author-email: Adam McKay <adam@beepboop.digital>
Requires-Python: >=3.10
Requires-Dist: dnspython>=2.6.1
Requires-Dist: rich>=13.6.0
Requires-Dist: typer>=0.9.0
Provides-Extra: dev
Requires-Dist: pytest>=8.0.0; extra == 'dev'
Requires-Dist: ruff>=0.2.0; extra == 'dev'
